parquet_metadata/__init__.py
parquet_metadata/__main__.py
parquet_metadata/parquet_metadata.py
parquet_metadata/test_parquet_metadata.py
parquet_metadata-0.0.1.dist-info/METADATA
parquet_metadata-0.0.1.dist-info/RECORD
parquet_metadata-0.0.1.dist-info/WHEEL
parquet_metadata-0.0.1.dist-info/entry_points.txt
parquet_metadata-0.0.1.dist-info/top_level.txt
