Metadata-Version: 2.1
Name: parquet-metadata
Version: 0.0.1
Summary: A tool to show metadata about a Parquet file
Home-page: https://github.com/cldellow/parquet-metadata
Author: Colin Dellow
Author-email: cldellow@cldellow.com
License: UNKNOWN
Platform: UNKNOWN
Classifier: Programming Language :: Python :: 3
Classifier: License :: OSI Approved :: Apache Software License
Classifier: Operating System :: OS Independent
